PythonSimpleFunctions/__init__.py
PythonSimpleFunctions/builder_for_flask_jsonify.py
PythonSimpleFunctions/check.py
PythonSimpleFunctions/cipher.py
PythonSimpleFunctions/convert.py
PythonSimpleFunctions/dictionarily.py
PythonSimpleFunctions/easy_sql.py
PythonSimpleFunctions/excellent_reader.py
PythonSimpleFunctions/memory.py
PythonSimpleFunctions/stackily.py
PythonSimpleFunctions/test.py
pythonsimplefunctions-1.0.8.dist-info/licenses/LICENSE
pythonsimplefunctions-1.0.8.dist-info/METADATA
pythonsimplefunctions-1.0.8.dist-info/WHEEL
pythonsimplefunctions-1.0.8.dist-info/top_level.txt
pythonsimplefunctions-1.0.8.dist-info/RECORD
