Metadata-Version: 2.4
Name: PythonSimpleFunctions
Version: 1.0.8
Summary: PyPI package designed to make development in Python easier.
Author-email: Isaiah Noel Salazar <isaiahnoelsalazar474@gmail.com>
License-File: LICENSE
Requires-Dist: openpyxl
Requires-Dist: unidecode
Dynamic: license-file
